torch_utilities/__init__.py
torch_utilities/audio.py
torch_utilities/augmentation.py
torch_utilities/io.py
torch_utilities/metrics.py
torch_utilities/modules.py
torch_utilities/pytorch.py
torch_utilities/utilities.py
torch_utilities/models/sig_bak_ovr.onnx
torch_utilities-1.2.4.dist-info/LICENSE
torch_utilities-1.2.4.dist-info/METADATA
torch_utilities-1.2.4.dist-info/WHEEL
torch_utilities-1.2.4.dist-info/top_level.txt
torch_utilities-1.2.4.dist-info/RECORD
