Metadata-Version: 2.1
Name: torch_utilities
Version: 1.2.4
Summary: Simplifying audio and deep learning with PyTorch.
Home-page: https://github.com/FedericoDiMarzo/torch_utilities
Author: Federico Di Marzo
Author-email: federicodimarzo@protonmail.com
Requires-Python: >=3.10
License-File: LICENSE
Requires-Dist: asteroid-filterbanks
Requires-Dist: multiprocess
Requires-Dist: onnxruntime
Requires-Dist: torchaudio
Requires-Dist: matplotlib
Requires-Dist: soundfile
Requires-Dist: resampy
Requires-Dist: loguru
Requires-Dist: torch
Requires-Dist: numpy
Requires-Dist: h5py
Requires-Dist: tqdm
Requires-Dist: pdoc
Provides-Extra: dev
Requires-Dist: pytest ; extra == 'dev'
Requires-Dist: build ; extra == 'dev'
Requires-Dist: twine ; extra == 'dev'
Requires-Dist: black ; extra == 'dev'
Requires-Dist: pdoc ; extra == 'dev'
